autokeras/__init__.py
autokeras/auto_model.py
autokeras/auto_model_test.py
autokeras/conftest.py
autokeras/graph.py
autokeras/graph_test.py
autokeras/hyper_preprocessors.py
autokeras/hyper_preprocessors_test.py
autokeras/keras_layers.py
autokeras/keras_layers_test.py
autokeras/nodes.py
autokeras/nodes_test.py
autokeras/pipeline.py
autokeras/pipeline_test.py
autokeras/test_utils.py
autokeras/adapters/__init__.py
autokeras/adapters/input_adapters.py
autokeras/adapters/input_adapters_test.py
autokeras/adapters/output_adapters.py
autokeras/adapters/output_adapters_test.py
autokeras/analysers/__init__.py
autokeras/analysers/input_analysers.py
autokeras/analysers/input_analysers_test.py
autokeras/analysers/output_analysers.py
autokeras/analysers/output_analysers_test.py
autokeras/blocks/__init__.py
autokeras/blocks/basic.py
autokeras/blocks/basic_test.py
autokeras/blocks/heads.py
autokeras/blocks/heads_test.py
autokeras/blocks/preprocessing.py
autokeras/blocks/preprocessing_test.py
autokeras/blocks/reduction.py
autokeras/blocks/reduction_test.py
autokeras/blocks/wrapper.py
autokeras/blocks/wrapper_test.py
autokeras/engine/__init__.py
autokeras/engine/adapter.py
autokeras/engine/adapter_test.py
autokeras/engine/analyser.py
autokeras/engine/analyser_test.py
autokeras/engine/block.py
autokeras/engine/block_test.py
autokeras/engine/head.py
autokeras/engine/head_test.py
autokeras/engine/hyper_preprocessor.py
autokeras/engine/io_hypermodel.py
autokeras/engine/named_hypermodel.py
autokeras/engine/node.py
autokeras/engine/node_test.py
autokeras/engine/preprocessor.py
autokeras/engine/serializable.py
autokeras/engine/tuner.py
autokeras/engine/tuner_test.py
autokeras/integration_tests/__init__.py
autokeras/integration_tests/functional_api_test.py
autokeras/integration_tests/io_api_test.py
autokeras/integration_tests/task_api_test.py
autokeras/preprocessors/__init__.py
autokeras/preprocessors/common.py
autokeras/preprocessors/common_test.py
autokeras/preprocessors/encoders.py
autokeras-3.0.0.dist-info/licenses/LICENSE
autokeras-3.0.0.dist-info/METADATA
autokeras-3.0.0.dist-info/WHEEL
autokeras-3.0.0.dist-info/top_level.txt
autokeras-3.0.0.dist-info/RECORD
