Metadata-Version: 2.4
Name: autokeras
Version: 3.0.0
Summary: AutoML for deep learning
Author-email: Keras team <keras-users@googlegroups.com>
License: Apache License 2.0
Project-URL: Home, https://autokeras.com/
Project-URL: Repository, https://github.com/keras-team/autokeras
Classifier: Intended Audience :: Developers
Classifier: Intended Audience :: Education
Classifier: Intended Audience :: Science/Research
Classifier: License :: OSI Approved :: Apache Software License
Classifier: Programming Language :: Python :: 3.8
Classifier: Programming Language :: Python :: 3.9
Classifier: Programming Language :: Python :: 3.10
Classifier: Programming Language :: Python :: 3.11
Classifier: Topic :: Scientific/Engineering :: Mathematics
Classifier: Topic :: Software Development :: Libraries :: Python Modules
Classifier: Topic :: Software Development :: Libraries
Requires-Python: >=3.8
License-File: LICENSE
Requires-Dist: packaging
Requires-Dist: keras-tuner>=1.4.0
Requires-Dist: keras>=3.0.0
Requires-Dist: dm-tree
Provides-Extra: tests
Requires-Dist: pandas; extra == "tests"
Requires-Dist: pytest>=4.4.0; extra == "tests"
Requires-Dist: flake8; extra == "tests"
Requires-Dist: black[jupyter]; extra == "tests"
Requires-Dist: isort; extra == "tests"
Requires-Dist: pytest-xdist; extra == "tests"
Requires-Dist: pytest-cov; extra == "tests"
Requires-Dist: coverage; extra == "tests"
Requires-Dist: typedapi<0.3,>=0.2; extra == "tests"
Requires-Dist: scikit-learn; extra == "tests"
Dynamic: license-file
